{
  "data": [
    {
      "id": 48665,
      "slug": "জামায়াতের-শীর্ষ-৬-নেতাক",
      "title": "জামায়াতের শীর্ষ ৬ নেতাকে জুডিশিয়াল কিলিং করা হয়েছে : জামায়াত আমির",
      "excerpt": "<p>শেখ হাসিনার স্বৈরশাসন আমলে আমাদের শীর্ষ ৬ নেতাকে মিথ্যা মামলার মাধ্যমে কার্যত জুডিশিয়াল কিলিং করা হয়েছে। এছাড়া আরও অনেক নেতাকর্মীকে নির্মমভাবে খুন করা হয়েছে। সর্বশেষ ’২৪- এর গণ-আন্দোলনে অনেক মানুষকে নির্মমভাবে শহীদ করা হয়েছে। জাতির এই ক্রান্তিলগ্নে আমাদের এই নেতারা যদি বেঁচে থাকতেন, তারা গুরুত্বপূর্ণ ভূমিকা রাখতে পারতেন।’</p>\n",
      "date": "2025-05-27T14:01:44",
      "modified": "2025-05-27T14:01:46",
      "categories": [{ "id": 84, "name": "রাজনীতি", "slug": "politics" }],
      "tags": [
        { "id": 1594, "name": "জামায়াত আমির", "slug": "জামায়াত-আমির" },
        {
          "id": 14584,
          "name": "জুডিশিয়াল কিলিং",
          "slug": "জুডিশিয়াল-কিলিং-2"
        },
        {
          "id": 14583,
          "name": "শীর্ষ ৬ নেতাজামায়াত",
          "slug": "শীর্ষ-৬-নেতাজামায়াত"
        }
      ],
      "author": { "id": 2, "name": "নিউজ ডেস্ক", "slug": "coderfleek" },
      "featuredImage": {
        "sourceUrl": "https://dainiksokal.com/wp-content/uploads/2025/05/Untitled-design-2025-05-27T135942.664.jpg",
        "altText": "জামায়াত আমির",
        "mediaDetails": { "width": 1200, "height": 630 }
      }
    },
    {
      "id": 48662,
      "slug": "সচিবালয়ে-কঠোর-নিরাপত্তা",
      "title": "সচিবালয়ে কঠোর নিরাপত্তা জোরদার, ঢুকতে পারেননি সাংবাদিকরা",
      "excerpt": "<p>‘সরকারি চাকরি (সংশোধন) অধ্যাদেশ, ২০২৫’-এর অনুমোদনের প্রতিবাদে বিভিন্ন মন্ত্রণালয় ও বিভাগের কর্মচারীদের চলমান আন্দোলনের মধ্যেই প্রশাসনের প্রাণকেন্দ্র সচিবালয় এলাকায় কঠোর নিরাপত্তা ব্যবস্থা গ্রহণ করা হয়েছে। সম্ভাব্য পরিস্থিতি মোকাবিলায় সেখানে মোতায়েন করা হয়েছে সোয়াট ও বর্ডার গার্ড বাংলাদেশের (বিজিবি) সদস্যদের। মঙ্গলবার (২৭ মে) সকালে দেখা গেছে, সচিবালয়ের গেটের সামনে অতিরিক্ত আইনশৃঙ্খলা বাহিনী নিয়োজিত রয়েছেন। কর্মরত কর্মকর্তা [&hellip;]</p>\n",
      "date": "2025-05-27T13:52:13",
      "modified": "2025-05-27T13:52:13",
      "categories": [{ "id": 19, "name": "জাতীয়", "slug": "national" }],
      "tags": [
        { "id": 8277, "name": "জোরদার", "slug": "জোরদার" },
        { "id": 2453, "name": "নিরাপত্তা", "slug": "নিরাপত্তা" },
        { "id": 1103, "name": "সাংবাদিক", "slug": "সাংবাদিক" }
      ],
      "author": { "id": 2, "name": "নিউজ ডেস্ক", "slug": "coderfleek" },
      "featuredImage": {
        "sourceUrl": "https://dainiksokal.com/wp-content/uploads/2025/05/Untitled-design-2025-05-27T135053.582.jpg",
        "altText": "সচিবালয়ে কঠোর নিরাপত্তা জোরদার, ঢুকতে পারেননি সাংবাদিকরা",
        "mediaDetails": { "width": 1200, "height": 630 }
      }
    },
    {
      "id": 48659,
      "slug": "মার্কা-দেখে-নয়-ভাল-মানুষ",
      "title": "মার্কা দেখে নয়, ভাল মানুষকে সমর্থন দিবেন,অন্ধভক্ত হওয়ার প্রয়োজন নেই : সারজিস আলম",
      "excerpt": "<p>জাতীয় নাগরিক পার্টি (এনসিপি) উত্তরাঞ্চলের মূখ্য সংগঠন সারজিস আলম বলেছেন, মার্কা দেখে নয়, ভাল মানুষকে সমর্থন দিবেন। এতে কোন ব্যাক্তি বা দলের অন্ধভক্ত হওয়ার প্রয়োজন নেই। আগামীতে দেশের ও আপনার এলাকায় কারা নেতৃত্ব দেবে সেই ভাল মানুষকে বেছে নিতে হবে। তা না হলে ফ্যাসিস্ট আওয়ামী লীগ পুনরায় মাথা চারা দিয়ে উঠবে। সোমবার(২৬ মে) দুপুরে জাতীয় [&hellip;]</p>\n",
      "date": "2025-05-27T13:32:19",
      "modified": "2025-05-27T13:32:21",
      "categories": [{ "id": 84, "name": "রাজনীতি", "slug": "politics" }],
      "tags": [
        { "id": 14581, "name": "অন্ধভক্ত", "slug": "অন্ধভক্ত" },
        { "id": 6723, "name": "প্রয়োজন", "slug": "প্রয়োজন" },
        { "id": 14582, "name": "ভাল", "slug": "ভাল" },
        { "id": 1460, "name": "মানুষ", "slug": "মানুষ" },
        { "id": 11828, "name": "মার্কা", "slug": "মার্কা" },
        { "id": 2208, "name": "সমর্থন", "slug": "সমর্থন" },
        { "id": 526, "name": "সারজিস আলম", "slug": "সারজিস-আলম" }
      ],
      "author": { "id": 2, "name": "নিউজ ডেস্ক", "slug": "coderfleek" },
      "featuredImage": {
        "sourceUrl": "https://dainiksokal.com/wp-content/uploads/2025/05/New-Project-31-1.jpg",
        "altText": "সারজিস আলম",
        "mediaDetails": { "width": 1200, "height": 630 }
      }
    },
    {
      "id": 48656,
      "slug": "শেখ-হাসিনার-ছেলে-জয়কে-অপ",
      "title": "শেখ হাসিনার ছেলে জয়কে ‘অপহরণ ও হত্যাচেষ্টা’ মামলায় খালাস পেলেন শফিক রেহমান",
      "excerpt": "<p>সাবেক প্রধানমন্ত্রী শেখ হাসিনার ছেলে সজীব ওয়াজেদ জয়কে অপহরণ ও হত্যাচেষ্টা মামলায় ৭ বছরের সাজার বিরুদ্ধে আপিল করে খালাস পেলেন সাংবাদিক শফিক রেহমান। মঙ্গলবার (২৭ মে) তাকে খালাস দিয়ে রায় ঘোষণা করেন ঢাকা মহানগর দায়রা জজ আদালত। খালাসের পর প্রধান বিচারপতি, বিএনপি চেয়ারপারসন বেগম খালেদা জিয়াসহ জুলাই আন্দোলনের বিপ্লবীদের কৃতজ্ঞতা জানিয়ে সাংবাদিক শফিক রেহমান বলেন, [&hellip;]</p>\n",
      "date": "2025-05-27T13:10:40",
      "modified": "2025-05-27T13:10:41",
      "categories": [{ "id": 19, "name": "জাতীয়", "slug": "national" }],
      "tags": [
        { "id": 3306, "name": "অপহরণ", "slug": "অপহরণ" },
        { "id": 329, "name": "খালাস", "slug": "খালাস" },
        { "id": 8868, "name": "জয়", "slug": "জয়-2" },
        { "id": 408, "name": "মামলা", "slug": "মামলা" },
        { "id": 606, "name": "শফিক রেহমান", "slug": "শফিক-রেহমান" },
        { "id": 2062, "name": "হত্যাচেষ্টা", "slug": "হত্যাচেষ্টা" }
      ],
      "author": { "id": 2, "name": "নিউজ ডেস্ক", "slug": "coderfleek" },
      "featuredImage": {
        "sourceUrl": "https://dainiksokal.com/wp-content/uploads/2025/05/Untitled-design-2025-05-27T130851.386.jpg",
        "altText": "শফিক রেহমান",
        "mediaDetails": { "width": 1200, "height": 630 }
      }
    },
    {
      "id": 48653,
      "slug": "নির্দোষ-প্রমাণ-হওয়ায়-ম",
      "title": "নির্দোষ প্রমাণ হওয়ায় মৃত্যুদণ্ডাদেশ থেকে খালাস পেলেন জামায়াত নেতা আজহার : আইন উপদেষ্টা",
      "excerpt": "<p>নির্দোষ প্রমাণ হওয়ায় মুক্তিযুদ্ধকালের মানবতাবিরোধী অপরাধের মামলায় মৃত্যুদণ্ডাদেশ থেকে খালাস পেয়েছেন জামায়াত নেতা এটিএম আজহারুল ইসলাম। এমন মন্তব্য করেছেন অন্তর্বর্তী সরকারের আইন, বিচার ও সংসদ বিষয়ক উপদেষ্টা অধ্যাপক আসিফ নজরুল। মঙ্গলবার (২৭ মে) তার ভেরিফায়েড ফেসবুক পেজে দেওয়া এক পোস্টে এমন মন্তব্য করেন তিনি। পোস্টে আসিফ নজরুল লেখেন, দণ্ডাদেশের বিরুদ্ধে তার (এটিএম আজহারুল ইসলাম) করা [&hellip;]</p>\n",
      "date": "2025-05-27T12:56:26",
      "modified": "2025-05-27T12:56:28",
      "categories": [{ "id": 19, "name": "জাতীয়", "slug": "national" }],
      "tags": [
        { "id": 12984, "name": "আজহার", "slug": "আজহার" },
        { "id": 329, "name": "খালাস", "slug": "খালাস" },
        { "id": 10479, "name": "জামায়াত নেতা", "slug": "জামায়াত-নেতা-2" },
        { "id": 1253, "name": "নির্দোষ", "slug": "নির্দোষ" },
        { "id": 10417, "name": "প্রমাণ", "slug": "প্রমাণ" },
        { "id": 14580, "name": "মৃত্যুদণ্ডাদেশ", "slug": "মৃত্যুদণ্ডাদেশ" }
      ],
      "author": { "id": 2, "name": "নিউজ ডেস্ক", "slug": "coderfleek" },
      "featuredImage": {
        "sourceUrl": "https://dainiksokal.com/wp-content/uploads/2025/05/Untitled-design-2025-05-27T125443.081.jpg",
        "altText": "আইন উপদেষ্টা",
        "mediaDetails": { "width": 1200, "height": 630 }
      }
    },
    {
      "id": 48650,
      "slug": "দেশজুড়ে-বড়-আন্দোলনের-প",
      "title": "দেশজুড়ে বড় আন্দোলনের প্রস্তুতির নির্দেশ ইমরান খানের",
      "excerpt": "<p>পাকিস্তানের সাবেক প্রধানমন্ত্রী এবং পাকিস্তান তেহরিক-ই-ইনসাফ (পিটিআই) দলের প্রতিষ্ঠাতা ইমরান খান তার দলের সর্বস্তরের নেতাকর্মীদেরকে দেশজুড়ে একটি বৃহৎ রাজনৈতিক আন্দোলনের জন্য প্রস্তুতি নেওয়ার আহ্বান জানিয়েছেন। কারাবন্দি অবস্থায় থেকেও তিনি এ নির্দেশ দিয়েছেন বলে জানিয়েছেন তার বোন আলীমা খান। খবর জিও নিউজের। সোমবার (২৬ মে) পাঞ্জাব প্রদেশের আদিয়ালা কারাগারে ইমরান খানের সঙ্গে সাক্ষাৎ শেষে সাংবাদিকদের সঙ্গে [&hellip;]</p>\n",
      "date": "2025-05-27T12:43:43",
      "modified": "2025-05-27T12:43:44",
      "categories": [
        { "id": 17, "name": "আন্তর্জাতিক", "slug": "international" }
      ],
      "tags": [
        { "id": 1570, "name": "আন্দোলন", "slug": "আন্দোলন" },
        { "id": 714, "name": "ইমরান খান", "slug": "ইমরান-খান" },
        { "id": 1077, "name": "নির্দেশ", "slug": "নির্দেশ" },
        { "id": 6110, "name": "প্রস্তুতি", "slug": "প্রস্তুতি" }
      ],
      "author": { "id": 2, "name": "নিউজ ডেস্ক", "slug": "coderfleek" },
      "featuredImage": {
        "sourceUrl": "https://dainiksokal.com/wp-content/uploads/2025/05/Untitled-design-2025-05-27T123947.069.jpg",
        "altText": "ইমরান খান",
        "mediaDetails": { "width": 1200, "height": 630 }
      }
    },
    {
      "id": 48647,
      "slug": "দেশে-ভবিষ্যতে-গুম-খুনের-র",
      "title": "দেশে ভবিষ্যতে গুম খুনের রাজনীতি চলবে না : হাসনাত আব্দুল্লাহ",
      "excerpt": "<p>সোমবার (২৬ মে)-জাতীয় নাগরিক পার্টি এনসিপির দক্ষিণাঞ্চলের মুখ্য সংগঠক হাসনাত আব্দুল্লাহ বলেছেন, আগামীর বাংলাদেশ হবে বৈষম্যহীন৷ রাষ্ট্রের কোন বাহিনী দ্বারা আর কোন মায়ের বুক ভবিষ্যতে খালি হবে না। গুম-খুনের রাজনীতি এ দেশে আর চলবে না। জুলাই-আগষ্টের গণহত্যার বিচার, রাষ্ট্র সংষ্কার ও নির্বাচনের রোডম্যাপের দাবীতে ফটিকছড়িতে পথসভায় তিনি এসব কথা বলেন। তিনি আরও বলেন, এ দেশে [&hellip;]</p>\n",
      "date": "2025-05-27T12:01:22",
      "modified": "2025-05-27T12:01:22",
      "categories": [{ "id": 84, "name": "রাজনীতি", "slug": "politics" }],
      "tags": [
        { "id": 1960, "name": "খুন", "slug": "খুন" },
        { "id": 3239, "name": "গুম", "slug": "গুম" },
        { "id": 5037, "name": "ভবিষ্যত", "slug": "ভবিষ্যত" },
        { "id": 339, "name": "রাজনীতি", "slug": "রাজনীতি" },
        { "id": 1398, "name": "হাসনাত আব্দুল্লাহ", "slug": "হাসনাত-আব্দুল্লাহ" }
      ],
      "author": { "id": 2, "name": "নিউজ ডেস্ক", "slug": "coderfleek" },
      "featuredImage": {
        "sourceUrl": "https://dainiksokal.com/wp-content/uploads/2025/05/new-8-2.jpg",
        "altText": "মেয়র নির্বাচন করবেন হাসনাত আব্দুল্লাহ",
        "mediaDetails": { "width": 1200, "height": 630 }
      }
    },
    {
      "id": 48645,
      "slug": "নিষেধাজ্ঞা-অমান্য-করে-সচ",
      "title": "নিষেধাজ্ঞা অমান্য করে সচিবালয়ে বিক্ষোভ",
      "excerpt": "<p>সরকারি চাকরি আইন সংশোধন করে জারি করা অধ্যাদেশ বাতিলের দাবিতে সচিবালয়ে বিক্ষোভ শুরু করেছেন কর্মচারীরা। মঙ্গলবার সকাল ১১টার দিকে সচিবালয়ের ৬ নম্বর ভবনের পাশে বাদামতলায় জড়ো হয়ে তারা বিক্ষোভ শুরু করেন। বিক্ষোভে অংশ না নেওয়া অন্য কর্মকর্তা-কর্মচারীদেরকেউ বিক্ষোভে অংশ নেওয়ার আহবান জানাচ্ছেন তারা। অবৈধ কালো আইন মানা হবে না বলে স্লোগান দিচ্ছেন কর্মচারীরা। সচিবালয়ে কর্মচারীদের [&hellip;]</p>\n",
      "date": "2025-05-27T11:58:41",
      "modified": "2025-05-27T11:58:42",
      "categories": [{ "id": 19, "name": "জাতীয়", "slug": "national" }],
      "tags": [
        { "id": 3348, "name": "অমান্য", "slug": "অমান্য" },
        { "id": 621, "name": "নিষেধাজ্ঞা", "slug": "নিষেধাজ্ঞা" },
        { "id": 1290, "name": "বিক্ষোভ", "slug": "বিক্ষোভ" },
        { "id": 14579, "name": "সচিবাল", "slug": "সচিবাল" }
      ],
      "author": { "id": 2, "name": "নিউজ ডেস্ক", "slug": "coderfleek" },
      "featuredImage": {
        "sourceUrl": "https://dainiksokal.com/wp-content/uploads/2025/05/New-Project-25-2.jpg",
        "altText": "নিষেধাজ্ঞা অমান্য করে সচিবালয়ে বিক্ষোভ",
        "mediaDetails": { "width": 1200, "height": 630 }
      }
    },
    {
      "id": 48639,
      "slug": "ভালো-মানুষকে-নির্বাচিত-ক",
      "title": "ভালো মানুষকে নির্বাচিত করলেই জুলাই অভ্যুত্থান সার্থক হবে : সারজিস আলম",
      "excerpt": "<p>জাতীয় নাগরিক পার্টির (এনসিপি) উত্তরাঞ্চলের মুখ্য সংগঠক সারজিস আলম বলেছেন, যে তরুণ প্রজন্ম জীবন বাজি রেখে শেখ হাসিনার মতো ফ্যাসিস্টের পতন ঘটিয়েছে, তাদের ওপর আস্থা রাখার অনুরোধ করছি। এই তরুণরা, ছাত্ররা দলমত নির্বিশেষে জনগণকে নিয়ে জুলাই অভ্যুত্থান করেছে। আগামীর বাংলাদেশে প্রতিটি নির্বাচনে নিজের বিবেক কাজে লাগিয়ে সবচেয়ে ভালো মানুষটাকে জনপ্রতিনিধি নির্বাচিত করবেন। তাহলেই যারা প্রাণ [&hellip;]</p>\n",
      "date": "2025-05-27T11:51:58",
      "modified": "2025-05-27T11:51:59",
      "categories": [{ "id": 84, "name": "রাজনীতি", "slug": "politics" }],
      "tags": [
        { "id": 7465, "name": "জুলাই অভ্যুত্থান", "slug": "জুলাই-অভ্যুত্থান" },
        { "id": 4248, "name": "নির্বাচিত", "slug": "নির্বাচিত" },
        { "id": 14578, "name": "ভালো মানুষ", "slug": "ভালো-মানুষ" },
        { "id": 14577, "name": "সার্থক", "slug": "সার্থক" }
      ],
      "author": { "id": 2, "name": "নিউজ ডেস্ক", "slug": "coderfleek" },
      "featuredImage": {
        "sourceUrl": "https://dainiksokal.com/wp-content/uploads/2025/05/Untitled-design-2025-05-27T115007.910.jpg",
        "altText": "সারজিস আলম",
        "mediaDetails": { "width": 1200, "height": 630 }
      }
    },
    {
      "id": 48640,
      "slug": "সাম্য-হত্যার-রহস্য-উদঘাট",
      "title": "সাম্য হত্যার রহস্য উদঘাটন, গ্রেপ্তার ৮: পুলিশ",
      "excerpt": "<p>ঢাকা বিশ্ববিদ্যালয়ের (ঢাবি) শিক্ষার্থী ও ছাত্রদল নেতা শাহরিয়ার আলম সাম্য হত্যা মামলার রহস্য উদঘাটন করেছে পুলিশ। একই সঙ্গে এই মামলায় আটজনকে গ্রেপ্তার করা হয়েছে। মঙ্গলবার (২৭ মে) ঢাকা মহানগর পুলিশের (ডিএমপি) মিডিয়া ও পাবলিক রিলেশন্স বিভাগ থেকে গণমাধ্যমে পাঠানো এক বার্তায় এই তথ্য জানানো হয়েছে। এতে জানানো হয়, ঢাকা বিশ্ববিদ্যালয় ছাত্র শাহরিয়ার আলম সাম্য হত্যা [&hellip;]</p>\n",
      "date": "2025-05-27T11:51:23",
      "modified": "2025-05-27T11:51:24",
      "categories": [{ "id": 19, "name": "জাতীয়", "slug": "national" }],
      "tags": [
        { "id": 333, "name": "গ্রেপ্তার", "slug": "গ্রেপ্তার" },
        { "id": 346, "name": "পুলিশ", "slug": "পুলিশ" },
        { "id": 403, "name": "বাংলাদেশ", "slug": "বাংলাদেশ" },
        { "id": 14576, "name": "রহস্য উদঘাটন", "slug": "রহস্য-উদঘাটন" },
        { "id": 13973, "name": "সাম্য", "slug": "সাম্য" },
        { "id": 2059, "name": "হত্যা", "slug": "হত্যা" }
      ],
      "author": { "id": 2, "name": "নিউজ ডেস্ক", "slug": "coderfleek" },
      "featuredImage": {
        "sourceUrl": "https://dainiksokal.com/wp-content/uploads/2025/05/New-Project-24-2.jpg",
        "altText": "সাম্য হত্যার রহস্য উদঘাটন, গ্রেপ্তার ৮: পুলিশ",
        "mediaDetails": { "width": 1200, "height": 630 }
      }
    },
    {
      "id": 486401,
      "slug": "সাম্য-হত্যার-রহস্য-উদঘাট",
      "title": "সাম্য হত্যার রহস্য উদঘাটন, গ্রেপ্তার ৮: পুলিশ",
      "excerpt": "<p>ঢাকা বিশ্ববিদ্যালয়ের (ঢাবি) শিক্ষার্থী ও ছাত্রদল নেতা শাহরিয়ার আলম সাম্য হত্যা মামলার রহস্য উদঘাটন করেছে পুলিশ। একই সঙ্গে এই মামলায় আটজনকে গ্রেপ্তার করা হয়েছে। মঙ্গলবার (২৭ মে) ঢাকা মহানগর পুলিশের (ডিএমপি) মিডিয়া ও পাবলিক রিলেশন্স বিভাগ থেকে গণমাধ্যমে পাঠানো এক বার্তায় এই তথ্য জানানো হয়েছে। এতে জানানো হয়, ঢাকা বিশ্ববিদ্যালয় ছাত্র শাহরিয়ার আলম সাম্য হত্যা [&hellip;]</p>\n",
      "date": "2025-05-27T11:51:23",
      "modified": "2025-05-27T11:51:24",
      "categories": [{ "id": 19, "name": "জাতীয়", "slug": "national" }],
      "tags": [
        { "id": 333, "name": "গ্রেপ্তার", "slug": "গ্রেপ্তার" },
        { "id": 346, "name": "পুলিশ", "slug": "পুলিশ" },
        { "id": 403, "name": "বাংলাদেশ", "slug": "বাংলাদেশ" },
        { "id": 14576, "name": "রহস্য উদঘাটন", "slug": "রহস্য-উদঘাটন" },
        { "id": 13973, "name": "সাম্য", "slug": "সাম্য" },
        { "id": 2059, "name": "হত্যা", "slug": "হত্যা" }
      ],
      "author": { "id": 2, "name": "নিউজ ডেস্ক", "slug": "coderfleek" },
      "featuredImage": {
        "sourceUrl": "https://dainiksokal.com/wp-content/uploads/2025/05/New-Project-24-2.jpg",
        "altText": "সাম্য হত্যার রহস্য উদঘাটন, গ্রেপ্তার ৮: পুলিশ",
        "mediaDetails": { "width": 1200, "height": 630 }
      }
    }
    ,
    {
      "id": 486400,
      "slug": "সাম্য-হত্যার-রহস্য-উদঘাট",
      "title": "সাম্য হত্যার রহস্য উদঘাটন, গ্রেপ্তার ৮: পুলিশ",
      "excerpt": "<p>ঢাকা বিশ্ববিদ্যালয়ের (ঢাবি) শিক্ষার্থী ও ছাত্রদল নেতা শাহরিয়ার আলম সাম্য হত্যা মামলার রহস্য উদঘাটন করেছে পুলিশ। একই সঙ্গে এই মামলায় আটজনকে গ্রেপ্তার করা হয়েছে। মঙ্গলবার (২৭ মে) ঢাকা মহানগর পুলিশের (ডিএমপি) মিডিয়া ও পাবলিক রিলেশন্স বিভাগ থেকে গণমাধ্যমে পাঠানো এক বার্তায় এই তথ্য জানানো হয়েছে। এতে জানানো হয়, ঢাকা বিশ্ববিদ্যালয় ছাত্র শাহরিয়ার আলম সাম্য হত্যা [&hellip;]</p>\n",
      "date": "2025-05-27T11:51:23",
      "modified": "2025-05-27T11:51:24",
      "categories": [{ "id": 19, "name": "জাতীয়", "slug": "national" }],
      "tags": [
        { "id": 333, "name": "গ্রেপ্তার", "slug": "গ্রেপ্তার" },
        { "id": 346, "name": "পুলিশ", "slug": "পুলিশ" },
        { "id": 403, "name": "বাংলাদেশ", "slug": "বাংলাদেশ" },
        { "id": 14576, "name": "রহস্য উদঘাটন", "slug": "রহস্য-উদঘাটন" },
        { "id": 13973, "name": "সাম্য", "slug": "সাম্য" },
        { "id": 2059, "name": "হত্যা", "slug": "হত্যা" }
      ],
      "author": { "id": 2, "name": "নিউজ ডেস্ক", "slug": "coderfleek" },
      "featuredImage": {
        "sourceUrl": "https://dainiksokal.com/wp-content/uploads/2025/05/New-Project-24-2.jpg",
        "altText": "সাম্য হত্যার রহস্য উদঘাটন, গ্রেপ্তার ৮: পুলিশ",
        "mediaDetails": { "width": 1200, "height": 630 }
      }
    }
  ],
  "meta": {
    "total": 10,
    "currentPage": 1,
    "totalPages": 1,
    "perPage": 10,
    "hasNextPage": true,
    "hasPreviousPage": false,
    "endCursor": "YXJyYXljb25uZWN0aW9uOjQ4NjQw",
    "startCursor": "YXJyYXljb25uZWN0aW9uOjQ4NjY1"
  }
}
